[
  {
    "Word": "cabbage",
    "Mean": "n.洋白菜  卷心菜  vt.偷窃"
  },
  {
    "Word": "cabin",
    "Mean": "n.小木屋  船舱 机舱 vt.抑制  vi.住在小屋"
  },
  {
    "Word": "cabinet",
    "Mean": "n.橱 柜 内阁 adj.私人的"
  },
  {
    "Word": "cable",
    "Mean": "n.缆 索 电缆 海底电报  vt.打海底电报   把...拧成缆  用缆捆 住 vi.打海底电报"
  },
  {
    "Word": "cafe",
    "Mean": "n.咖啡馆  小餐厅"
  },
  {
    "Word": "cafeteria",
    "Mean": "n.自助食堂  adj.有多种选择的"
  },
  {
    "Word": "cage",
    "Mean": "n.笼 鸟笼 囚笼 监狱 笼状结构  vt.关入笼中"
  },
  {
    "Word": "cake",
    "Mean": "n.饼 糕 蛋糕 块状物  小菜一碟(容易做成的事)    vt.涂厚厚的 一层 覆盖 填满 vi.结成块"
  },
  {
    "Word": "calculate",
    "Mean": "vt.计算  估计 考虑 推测 计划 vi.计算  预测 依赖"
  },
  {
    "Word": "calculation",
    "Mean": "n.计算  计算结果"
  },
  {
    "Word": "calculator",
    "Mean": "n.计算器  计算者"
  },
  {
    "Word": "calendar",
    "Mean": "n.日历  月历 日程表  历书 历法 vt.进入日历"
  },
  {
    "Word": "call",
    "Mean": "n.呼叫  访问 打电话  请求 把...看作  vt.把...叫做   叫 喊 呼 叫 访问 打电话  vi.(短暂的)拜访   呼叫"
  },
  {
    "Word": "calm",
    "Mean": "n.平稳  风平浪静  adj.静的  平静的  冷静的  vt. & vi.平静下 来 镇静"
  },
  {
    "Word": "camel",
    "Mean": "n.骆驼  浮船箱  浅黄棕色"
  },
  {
    "Word": "camera",
    "Mean": "n.照相机  摄影机  罗马教廷的财政部"
  },
  {
    "Word": "camp",
    "Mean": "n.野营  营地 兵营 露营 帐棚 训练营  做作 vt. & vi.露营  扎 营 做作 adj.做作的"
  },
  {
    "Word": "campaign",
    "Mean": "n.战役  运动 活动 vt.参加竞赛  vi.(从事、组织)活动"
  },
  {
    "Word": "campus",
    "Mean": "n.校园  学校场地"
  },
  {
    "Word": "can",
    "Mean": "aux.v.能  会 可能 n.罐头  听头 容器 vt.罐装  vt.炒某人鱿鱼"
  },
  {
    "Word": "Canada",
    "Mean": "n.加拿大"
  },
  {
    "Word": "Canadian",
    "Mean": "adj.加拿大的   加拿大人的  n.加拿大人"
  },
  {
    "Word": "canal",
    "Mean": "n.运河  沟渠 管 气管 食管 vt.建运河  疏导"
  },
  {
    "Word": "cancel",
    "Mean": "n.取消  撤消 vt.取消  撤消 删去 约分 vi.抵消"
  },
  {
    "Word": "cancer",
    "Mean": "n.癌 癌症 肿瘤 巨蟹座"
  },
  {
    "Word": "candidate",
    "Mean": "n.候选人  投考者  求职者"
  },
  {
    "Word": "candle",
    "Mean": "n.蜡烛  烛形物  烛光"
  },
  {
    "Word": "candy",
    "Mean": "n.糖果  砂糖结晶  vt.用糖煮  使结晶为砂糖   vi.结晶为砂糖"
  },
  {
    "Word": "cannon",
    "Mean": "n.大炮  火炮 榴弹炮  v.开炮"
  },
  {
    "Word": "canoe",
    "Mean": "n.独木舟  皮艇 划子 轻舟 v.乘独木舟"
  },
  {
    "Word": "canon",
    "Mean": "n. 教会法规  标准、准则  正典 正式名单  教堂里的教士   佳能 (财富500强公司之一    总部所在地日本   主要经营办公设备)"
  },
  {
    "Word": "canteen",
    "Mean": "n.小卖部  临时餐室  食堂"
  },
  {
    "Word": "canvas",
    "Mean": "n.粗帆布  一块油画布  (帆布)画布  油画"
  },
  {
    "Word": "cap",
    "Mean": "n.帽子  便帽 帽状物  盖子 顶 vt.给戴帽  覆盖顶端  超过 形成 化学键于  抑制 vi.形成化学键"
  },
  {
    "Word": "capable",
    "Mean": "adj.有能力的   有才能的  足以胜任的  有...倾向的"
  },
  {
    "Word": "capacity",
    "Mean": "n.容量  能力 能量 容积 资格 职位 adj.(达到最大容量)满的"
  },
  {
    "Word": "capital",
    "Mean": "n.资本  资金 首都 大写字母  adj.大写的  资本的  首要的"
  },
  {
    "Word": "captain",
    "Mean": "n.陆军上尉  队长 船长 首领 vt.率领  指挥"
  },
  {
    "Word": "captive",
    "Mean": "n.俘虏  被监禁的人  迷恋者  adj.被俘的  被迷住的"
  },
  {
    "Word": "capture",
    "Mean": "n.抓取  战利品  捕获之物  vt.捕获  俘获 夺得 抓取 获得 迷住"
  },
  {
    "Word": "car",
    "Mean": "n.汽车  小汽车  轿车 车厢 吊舱"
  },
  {
    "Word": "carbon",
    "Mean": "n.碳 灯芯 复写纸"
  },
  {
    "Word": "card",
    "Mean": "n.卡 卡片 名片 纸牌 打牌 节目单  vt.附上或提供卡片   印卡 在卡片上列出   检查资格"
  },
  {
    "Word": "care",
    "Mean": "n.小心  照料 忧虑 慎思 焦虑因素  vi.关心  介意 照顾 喜爱 vt.介意  希望 abbr.=Cooperative   for American  Remittances to Europe  汇款到欧洲合作社"
  },
  {
    "Word": "career",
    "Mean": "n.生涯  职业 事业 经历 vi.猛冲  飞跑 vt.在...中急行"
  },
  {
    "Word": "careful",
    "Mean": "adj.小心的  仔细的  细致的"
  },
  {
    "Word": "careless",
    "Mean": "adj.粗心的  漫不经心的  疏忽的  n.不关心的  粗心的 [反]attentive"
  },
  {
    "Word": "cargo",
    "Mean": "n.船货  货物"
  },
  {
    "Word": "carpenter",
    "Mean": "n.木工  木匠 v.做木工活"
  },
  {
    "Word": "carpet",
    "Mean": "n.地毯  毡毯 毛毯 vt.铺以地毯  铺盖"
  },
  {
    "Word": "carriage",
    "Mean": "n.客车厢  四轮马车"
  },
  {
    "Word": "carrier",
    "Mean": "n.运输工具  运载工具  运送者  行李架  客运公司  航空母舰  带 菌者 电信公司"
  },
  {
    "Word": "carrot",
    "Mean": "n.胡罗卜  报酬 好处"
  },
  {
    "Word": "carry",
    "Mean": "n. 搬运 射程 投射 联运 vt. 负载 承担 携带 运载 运输 传 送 传播 表达 带有 容纳 怀孕 延续 推动 赢得 记录 vi. 负载 被传达  容许被运输  被通过"
  },
  {
    "Word": "cart",
    "Mean": "n.(二轮或四轮)运货马车    手推车  vt.用马车装载   用手提(笨重 物品) 强行带走"
  },
  {
    "Word": "carve",
    "Mean": "vt.刻 雕刻 切开 vi.雕刻  切割"
  },
  {
    "Word": "case",
    "Mean": "n.情况  事实 实情 病例 箱(子)  盒(子)  套 案例 vt.装箱  踩 点"
  },
  {
    "Word": "cash",
    "Mean": "n.现金  现款 vt.兑现  付现款  adj.现金的"
  },
  {
    "Word": "cassette",
    "Mean": "n.盒式录音带   盒子 匣子 盒式录音机"
  },
  {
    "Word": "cast",
    "Mean": "n.演员阵容  投掷 vt.投 扔 抛 浇铸"
  },
  {
    "Word": "castle",
    "Mean": "n.城堡  巨大建筑物  vt.置于城堡中   (棋)移动王车易位 vi.(棋)移动王车易位"
  },
  {
    "Word": "casual",
    "Mean": "adj.偶然的  随便的  非正式  漫不经心的"
  },
  {
    "Word": "cat",
    "Mean": "n.猫 猫科 猫皮 邪恶的女人  吊锚机  单帆小船  vt.吊锚  vi.寻 找性交伴侣  (CAT)电子计算机横断层扫描"
  },
  {
    "Word": "catalog",
    "Mean": "n. 目录 目录册  大学概况手册   商品型录  vt. 做目录  分类说 明 名入列表  vi. 研究(手册或目录)   (商品)在型录中明码标价"
  },
  {
    "Word": "catch",
    "Mean": "n.捕捉  陷阱 捕获物  接(球等)  扣栓物  隐患 vt. 捉住 赶上 领会 了解 感染 被钩住  击中 察觉 vi. 抓住 燃着"
  },
  {
    "Word": "cathedral",
    "Mean": "n.总教堂  大教堂"
  },
  {
    "Word": "cattle",
    "Mean": "n.牛 牲口 家畜 畜牲(复数)"
  },
  {
    "Word": "cause",
    "Mean": "n.原因  理由 事业 vt.引起  使发生"
  },
  {
    "Word": "cave",
    "Mean": "n.山洞  洞穴 窑洞 vt.挖空  塌落 屈服 vi.塌落"
  },
  {
    "Word": "cease",
    "Mean": "vi. &vi. &n.停止  终了 停息"
  },
  {
    "Word": "ceiling",
    "Mean": "n.天花板  顶蓬 上限"
  },
  {
    "Word": "celebrate",
    "Mean": "vt.庆祝  歌颂 赞美 vi.庆祝  祝贺 颂扬"
  },
  {
    "Word": "cell",
    "Mean": "n.细胞  小房间  电池 小组 单人牢房  (蜂房的)巢室   手机"
  },
  {
    "Word": "cellar",
    "Mean": "n.地窑  地下室  vt.把...藏入地窑(或酒窑)"
  },
  {
    "Word": "cement",
    "Mean": "n.水泥  胶泥 纽带 接合剂  牙骨质  补牙物  基石 vt.粘结  接合 用水泥涂  vi.接合起来"
  },
  {
    "Word": "cent",
    "Mean": "n.分 分币 百(分之)"
  },
  {
    "Word": "center",
    "Mean": "n.中心  中间 主角 中锋 重点 vi.居中  聚焦于...  vt.使集中 放在中央"
  },
  {
    "Word": "centigrade",
    "Mean": "adj.百分度的   摄氏的"
  },
  {
    "Word": "centimetre",
    "Mean": "n.公分  厘米=centimeter(美)"
  },
  {
    "Word": "central",
    "Mean": "adj.中心的  主要的  基本的  折中的  中枢的  n.电话交流  中央 办公室  中心"
  },
  {
    "Word": "centre",
    "Mean": "n.中心  中枢 聚集点  vt.集中  置于中央  关注于  vi.居中"
  },
  {
    "Word": "century",
    "Mean": "n.世纪  一百年  成百的东西"
  },
  {
    "Word": "ceremony",
    "Mean": "n.典礼  仪式 礼节 礼仪"
  },
  {
    "Word": "certain",
    "Mean": "adj.确实的  肯定的  必然的  特定的  pron.某几个  某些"
  },
  {
    "Word": "certainly",
    "Mean": "adv.一定  必定 当然"
  },
  {
    "Word": "certainty",
    "Mean": "n.必然  肯定 确定 确实的事情"
  },
  {
    "Word": "certificate",
    "Mean": "n.证(明)书  证件 执照 vt.批准  认可 发证书给..."
  },
  {
    "Word": "chain",
    "Mean": "n.链 链条 项圈 连锁 束缚 vt.用铁练锁住   束缚 囚禁"
  },
  {
    "Word": "chair",
    "Mean": "n.椅子  主席 席位 讲座 要职 vt.上任  使担任(某事务)的主席 主持"
  },
  {
    "Word": "chairman",
    "Mean": "n.主席  议长 会长"
  },
  {
    "Word": "chalk",
    "Mean": "n.白垩  粉笔 v.用粉笔写  记录"
  },
  {
    "Word": "challenge",
    "Mean": "n.挑战  要求 需要 v.向...挑战"
  },
  {
    "Word": "chamber",
    "Mean": "n.会议室  房间 会所 室 腔 vt.装入室中(枪膛)   adj.室内演奏 的"
  },
  {
    "Word": "champion",
    "Mean": "n.冠军  得胜者  拥护者  勇士 vt.保卫  拥护"
  },
  {
    "Word": "chance",
    "Mean": "n.机会  意外 运气 风险 可能性  vi.偶然发生  vt.偶然发生  冒 险"
  },
  {
    "Word": "change",
    "Mean": "n.改变  变化 零钱 vt. & vi.改变"
  },
  {
    "Word": "channel",
    "Mean": "n.海峡  渠道 通道 频道 方法 vt.引导  开导 形成河道  输送"
  },
  {
    "Word": "chapter",
    "Mean": "n.章 回 篇 牧师的例行会议   地方分会"
  },
  {
    "Word": "character",
    "Mean": "n.性格  个性 品质 特性 角色 字符 人物 名誉 地位 adj. [剧](角色)代表某一特性的"
  },
  {
    "Word": "characteristic",
    "Mean": "adj.特有的  典型的  n.特性  特征 特色"
  },
  {
    "Word": "charge",
    "Mean": "vt. & vi.索价  控告 加罪于  要价 赊帐 充电 管理 n.电荷  指 控 费用 照顾 责任"
  },
  {
    "Word": "charity",
    "Mean": "n.施舍  慈善事业  慈善 慈善机关(团体)   仁慈 宽厚"
  },
  {
    "Word": "charming",
    "Mean": "adj迷人的  可爱的"
  },
  {
    "Word": "chart",
    "Mean": "n.图 图表 海图 vt.制成图表"
  },
  {
    "Word": "chase",
    "Mean": "n.追逐  追赶 追求 狩猎 争取 vt.追捕  狩猎"
  },
  {
    "Word": "cheap",
    "Mean": "adj.廉价的  便宜的  劣质的  品质低的  虚伪的  adv.便宜地"
  },
  {
    "Word": "cheat",
    "Mean": "n.骗子  欺骗行为  vt.骗取  哄 作弊 vi.行骗  作弊"
  },
  {
    "Word": "check",
    "Mean": "vt.检查  制止 阻止 核对 (国际象棋)将军   n.检查  支票 账单 制止 阻止物  检验标准  (国际象棋)将军"
  },
  {
    "Word": "cheek",
    "Mean": "n.面颊  脸蛋 vt.粗鲁地向...讲"
  },
  {
    "Word": "cheer",
    "Mean": "n.愉快  激励 欢呼 vt.欢呼  加油 鼓舞 快活起来  vi.使振奋 欢呼"
  },
  {
    "Word": "cheerful",
    "Mean": "adj.快乐的  愉快的"
  },
  {
    "Word": "cheese",
    "Mean": "n.乳酪  干酪 要求照相的人说的口形词    vt.停止"
  },
  {
    "Word": "chemical",
    "Mean": "adj.化学的  n.化学制品"
  },
  {
    "Word": "chemist",
    "Mean": "n.化学家  药剂师"
  },
  {
    "Word": "chemistry",
    "Mean": "n.化学  化学性质  相互作用"
  },
  {
    "Word": "cheque",
    "Mean": "n.支票"
  },
  {
    "Word": "cherry",
    "Mean": "n.樱桃 樱桃树 樱桃色"
  },
  {
    "Word": "chess",
    "Mean": "n.棋 国际象棋"
  },
  {
    "Word": "chest",
    "Mean": "n.胸腔  胸膛 (大)箱子  金库 资金 一箱 密封室：衣橱"
  },
  {
    "Word": "chew",
    "Mean": "vt.咀嚼  嚼碎 损坏 vi.咀嚼  n.咀嚼  咀嚼物"
  },
  {
    "Word": "chicken",
    "Mean": "n.小鸡  小鸟 鸡肉 胆小 懦夫 adj.懦弱的  胆小的"
  },
  {
    "Word": "chief",
    "Mean": "adj.主要的  首席的  n.首领"
  },
  {
    "Word": "child",
    "Mean": "n.小孩  儿童 儿子 产物"
  },
  {
    "Word": "childhood",
    "Mean": "n.童年  幼年 早期"
  },
  {
    "Word": "childish",
    "Mean": "adj.孩子气的   幼稚的  简单的  年老糊涂的"
  },
  {
    "Word": "chill",
    "Mean": "vt. 使变冷  使...寒心  冷冻 使...惊恐  使泄气  vi. 变冷 发 抖 凝固 感到寒冷  n. 寒冷 寒意 失意 恐惧 adj. 寒冷的  冷漠 的 感冒的  扫兴的"
  },
  {
    "Word": "chimney",
    "Mean": "n.烟囱  烟筒 玻璃罩"
  },
  {
    "Word": "chin",
    "Mean": "n.颏 下巴 vt.做单杠  vi.作引体向上   聊天"
  },
  {
    "Word": "China",
    "Mean": "n.中国"
  },
  {
    "Word": "china",
    "Mean": "n.瓷器  瓷料"
  },
  {
    "Word": "Chinese",
    "Mean": "adj.中国的  n.中国人  汉语"
  },
  {
    "Word": "chocolate",
    "Mean": "n.巧克力  巧克力糖  巧克力饮品  adj.巧克力的   有巧克力糖衣 的 巧克力色的"
  },
  {
    "Word": "choice",
    "Mean": "n.选择  挑选 抉择 adj.上等的  精选的"
  },
  {
    "Word": "choke",
    "Mean": "vt.(掐住或阻塞气管)使(某人)停止呼吸      塞满 vi.窒息  阻塞 n.窒息  阻风门开关  阻塞"
  },
  {
    "Word": "choose",
    "Mean": "vt.选择  挑选 情愿 vi.选择"
  },
  {
    "Word": "chop",
    "Mean": "vt.砍(价)  劈 切(细)  剁碎 vi.砍 n.厚肉片  排骨 砍"
  },
  {
    "Word": "Christian",
    "Mean": "n.基督教徒  信徒 adj.基督教(徒)的   信奉基督教的   仁慈的"
  },
  {
    "Word": "Christmas",
    "Mean": "n.圣诞节"
  },
  {
    "Word": "church",
    "Mean": "n.教堂  礼拜堂  礼拜仪式  基督教徒  教会 adj.教堂的  vt. 把...带到教堂接受某种宗教仪式"
  },
  {
    "Word": "cigarette",
    "Mean": "n.香烟  纸烟 卷烟"
  },
  {
    "Word": "cinema",
    "Mean": "n.电影院  电影 影片"
  },
  {
    "Word": "circle",
    "Mean": "n.圆 圆周 圈子 社交圈  循环 vt. & vi.包围  盘旋 环绕"
  },
  {
    "Word": "circuit",
    "Mean": "n.电路  环行 一圈 巡行 巡回vt.  & vi.巡回"
  },
  {
    "Word": "circular",
    "Mean": "adj.圆的  循环的  n.传单  通报"
  },
  {
    "Word": "circulate",
    "Mean": "vt.使循环  使流通  vi.流通  循环 传播"
  },
  {
    "Word": "circumference",
    "Mean": "n.圆周  周长 周围 圆周线  胸围"
  },
  {
    "Word": "circumstance",
    "Mean": "n.情况  条件 境遇 环境 (复数)境况  事件 详情"
  },
  {
    "Word": "citizen",
    "Mean": "n.公民  市民 居民"
  },
  {
    "Word": "city",
    "Mean": "n.城市  都市"
  },
  {
    "Word": "civil",
    "Mean": "adj.国内的  公民的  文职的  文明的  有礼貌的  民用的"
  },
  {
    "Word": "civilization",
    "Mean": "n.文明  文化 开化"
  },
  {
    "Word": "civilize",
    "Mean": "vt.使文明  教育"
  },
  {
    "Word": "claim",
    "Mean": "vt.要求  请求 声称 主张 断言 索取 n.要求  要求权  主张 断 言 声称 要求物"
  },
  {
    "Word": "clap",
    "Mean": "vi.拍手  砰的一声  突然离开  vt.拍 轻拍 轻敲 鼓掌 击掌 急 速放置  n.拍手  拍手声  一阵强风"
  },
  {
    "Word": "clarify",
    "Mean": "vt.澄清  阐明 使...明晰"
  },
  {
    "Word": "clasp",
    "Mean": "n.扣子  钩子 别针 紧握 v.扣紧  紧握 密切合作"
  },
  {
    "Word": "class",
    "Mean": "n.班 班级 (等)阶级  种类 vt.分类"
  },
  {
    "Word": "classical",
    "Mean": "adj.古典的  经典的  典雅的"
  },
  {
    "Word": "classification",
    "Mean": "n.分类  分级 分类法"
  },
  {
    "Word": "classify",
    "Mean": "vt.把...分类   分类 归类"
  },
  {
    "Word": "classmate",
    "Mean": "n.同班同学"
  },
  {
    "Word": "classroom",
    "Mean": "n.教室  课堂"
  },
  {
    "Word": "claw",
    "Mean": "n.爪 钳 脚爪 螯 爪状物  vt. & vi.抓 撕"
  },
  {
    "Word": "clay",
    "Mean": "n.粘土  泥土 肉体"
  },
  {
    "Word": "clean",
    "Mean": "adj.清洁的  干净的  纯洁的  正当的  完全的  精准的  空的 adv. 完全地  n.清洁  vt. & vi.打扫  清扫"
  },
  {
    "Word": "clear",
    "Mean": "adj. 清晰的  清楚的  明确的  澄清的  头脑清醒的  vt. 清除 清 除障碍  澄清 使明亮  明确 vi. 变清晰  消失 放晴 adv. 清楚地 一直 n. 间隙 空地 开旷的地方"
  },
  {
    "Word": "clearly",
    "Mean": "adv.明白地  清晰地  adj.清楚的"
  },
  {
    "Word": "clerk",
    "Mean": "n.店员  办事员  职员"
  },
  {
    "Word": "clever",
    "Mean": "adj.聪明的  机敏的"
  },
  {
    "Word": "cliff",
    "Mean": "n.悬崖  峭壁"
  },
  {
    "Word": "climate",
    "Mean": "n.气候  风土 地带 风气 气氛"
  },
  {
    "Word": "climb",
    "Mean": "vt. & vi.攀登  爬 上升 n.攀登(处)"
  },
  {
    "Word": "cloak",
    "Mean": "n.斗篷  覆盖(物)  宽大外衣  掩护 v.遮掩  隐匿"
  },
  {
    "Word": "clock",
    "Mean": "n.钟 时钟 计时器  仪表"
  },
  {
    "Word": "close",
    "Mean": "vt.关闭  结束 靠近 vi. 关 停业 搏斗 n. 完结 结论 adj. 靠 近的 亲近的  几乎 密切的  势均力敌的adv.   紧挨着  紧紧地"
  },
  {
    "Word": "closely",
    "Mean": "adv.紧密地  接近地  严密地"
  },
  {
    "Word": "cloth",
    "Mean": "n.布 衣料 桌布"
  },
  {
    "Word": "clothe",
    "Mean": "vt.给...穿衣服   穿上 覆上 授以 赋予 表达"
  },
  {
    "Word": "clothes",
    "Mean": "n.衣服  服装 被褥"
  },
  {
    "Word": "clothing",
    "Mean": "n.(总称)衣服   被褥"
  },
  {
    "Word": "cloud",
    "Mean": "n.云 云状物  云状的烟  阴影 vt.使...模糊  以云遮敝  笼罩 使 ...混淆  毁坏 vi.脸色显得阴沉"
  },
  {
    "Word": "cloudy",
    "Mean": "adj.多云的  云一般的"
  },
  {
    "Word": "club",
    "Mean": "n.俱乐部  夜总会  击棍 扑克牌中的梅花   vt.用棍棒打  集合 vi.集合  分担花费  泡夜总会"
  },
  {
    "Word": "clue",
    "Mean": "n.线索  暗示 提示 vt.提示"
  },
  {
    "Word": "clumsy",
    "Mean": "adj.笨拙的  笨重的  愚笨的  不得体的"
  },
  {
    "Word": "coach",
    "Mean": "n.长途公共汽车   大巴 教练 (火车)客车车厢   四轮马车  经济舱 vt. & vi.训练  指导"
  },
  {
    "Word": "coal",
    "Mean": "n.煤 煤块 木炭 运煤工  vt.烧成炭  供应煤  vi.装煤  加煤"
  },
  {
    "Word": "coarse",
    "Mean": "adj.粗的  粗糙的  非精制的  粗俗的"
  },
  {
    "Word": "coast",
    "Mean": "n.海岸  海滨(地区)  滑坡 vt.沿海岸而行   vi.下滑"
  },
  {
    "Word": "coat",
    "Mean": "n.外套  上衣 表皮 动物皮毛  一层 vt.外面覆盖  盖上毛衣"
  },
  {
    "Word": "cock",
    "Mean": "n.公鸡  雄禽 旋塞 (男子间友好的互称用语)老兄     阴茎 vt.立 起 竖起 vi.昂首阔步地走"
  },
  {
    "Word": "code",
    "Mean": "n.码 密码 法规 准则 法典 代码 vt.把...编码   制成法典"
  },
  {
    "Word": "coffee",
    "Mean": "n.咖啡  咖啡茶"
  },
  {
    "Word": "coil",
    "Mean": "n.(一)卷  线圈 骚动 【电】线圈  绕组 vt. & vi.盘绕  卷"
  },
  {
    "Word": "coin",
    "Mean": "n.硬币  金钱 货币 铸造(硬币)  vt.制造钱币  创造 adj.与硬币 有关的"
  },
  {
    "Word": "cold",
    "Mean": "adj.冷的  冷淡的  漠然的  客观的  n.冷 感冒 低温 adv.唐突地 无回旋余地地   即兴地"
  },
  {
    "Word": "collapse",
    "Mean": "vi.倒坍  崩溃 瓦解 折叠 vt.倒塌  缩减 n.崩溃  倒塌 暴跌"
  },
  {
    "Word": "collar",
    "Mean": "n.衣领  项圈 vt.抓住  为...戴上项圈"
  },
  {
    "Word": "colleague",
    "Mean": "n.同事  同僚"
  },
  {
    "Word": "collect",
    "Mean": "vt.收集  推论 接走 vi.收款  聚集 积累 adj. & adv.对方付费 (的)"
  },
  {
    "Word": "collection",
    "Mean": "n.搜集  收集 收藏品  小组 集合"
  },
  {
    "Word": "collective",
    "Mean": "adj.集体的  共同的  集合性的  n.集体"
  },
  {
    "Word": "college",
    "Mean": "n.学院  学校 社团 枢机主教团  大学"
  },
  {
    "Word": "collision",
    "Mean": "n.碰撞  冲突"
  },
  {
    "Word": "colonel",
    "Mean": "n.陆军上校  中校"
  },
  {
    "Word": "colony",
    "Mean": "n.侨民  殖民地  侨居地  聚居(地)"
  },
  {
    "Word": "color",
    "Mean": "n.颜色  彩色 颜料 气色 风格 vt.把...涂颜色   粉饰 vi.脸红"
  },
  {
    "Word": "column",
    "Mean": "n.柱 支柱 圆柱 柱形物  专栏 [计算机]列"
  },
  {
    "Word": "comb",
    "Mean": "n.梳子  梳状物  鸡冠 蜂巢 vt.梳理  清理 搜查 用梳子  vi.搜 寻"
  },
  {
    "Word": "combination",
    "Mean": "n.结合  联合 化合 联合体"
  },
  {
    "Word": "combine",
    "Mean": "vt.使结合  兼有 融合 联结 收割 混合谷物  vi.结合  联合 n. 集团 联合收割机"
  },
  {
    "Word": "come",
    "Mean": "vi.来 来到 达到 出现 发生 进入 vt.接近  扮演"
  },
  {
    "Word": "comfort",
    "Mean": "n.舒适  安慰 安慰者  vt.安慰"
  },
  {
    "Word": "comfortable",
    "Mean": "adj.舒适的  安慰的  充裕的"
  },
  {
    "Word": "command",
    "Mean": "vt.命令  指挥 控制 支配 n.命令  指挥 控制 [计算机]DOS命 令：引用辅助命令处理器"
  },
  {
    "Word": "commander",
    "Mean": "n.司令官  指挥员"
  },
  {
    "Word": "comment",
    "Mean": "n.评论  意见 注释 闲话 v.注释  评论"
  },
  {
    "Word": "commerce",
    "Mean": "n.商业  贸易 社交"
  },
  {
    "Word": "commercial",
    "Mean": "adj.商业的  商品化的  n.商业广告"
  },
  {
    "Word": "commission",
    "Mean": "n.委任(状)  任官令  委员会  佣金 犯罪行为  vt.委任  委托 使 服役"
  },
  {
    "Word": "commit",
    "Mean": "vt.犯(错误)  干(坏事)  委托(托付)  作...事  承诺 [计算机]委 托"
  },
  {
    "Word": "committee",
    "Mean": "n.委员会  全体委员"
  },
  {
    "Word": "common",
    "Mean": "adj.普通的  共同的  平常的  n.平民  普通 公地 公园"
  },
  {
    "Word": "commonly",
    "Mean": "adv.普通地  一般地  通常地"
  },
  {
    "Word": "communicate",
    "Mean": "vi.通讯  传达 传播 vi.交流  沟通 联通"
  },
  {
    "Word": "communication",
    "Mean": "n.通讯  传达 交通 信息 [计算机]通信"
  },
  {
    "Word": "communism",
    "Mean": "n.共产主义"
  },
  {
    "Word": "Communism",
    "Mean": "n.共产主义学说   共产主义制度"
  },
  {
    "Word": "communist",
    "Mean": "n.共产党员  共产主义者  adj.共产主义的"
  },
  {
    "Word": "community",
    "Mean": "n.社区  团体 社会 公社 群落(生)"
  },
  {
    "Word": "companion",
    "Mean": "n.同伴  同事 共事者  伴侣 成对物品之一   (船的)甲板间扶梯 (或扶梯的顶篷)   vt. & vi.陪伴"
  },
  {
    "Word": "company",
    "Mean": "n.公司  商号 同伴 客人 一群 连队 vt.陪伴  vi.联合"
  },
  {
    "Word": "comparative",
    "Mean": "adj.比较的  相对的  n.对手"
  },
  {
    "Word": "compare",
    "Mean": "vt. & vi.比较  对照 比作 比喻 n.比较  对照"
  },
  {
    "Word": "comparison",
    "Mean": "n.比较  对照 比似"
  },
  {
    "Word": "compass",
    "Mean": "n.罗盘  指南针  圆规 vt.图谋  包围 达成"
  },
  {
    "Word": "compel",
    "Mean": "vt.强迫  迫使屈服"
  },
  {
    "Word": "compete",
    "Mean": "vi.比赛  竞争 对抗"
  },
  {
    "Word": "competent",
    "Mean": "adj.有能力的   胜任的  足够的  应该做的"
  },
  {
    "Word": "competition",
    "Mean": "n.竞争  比赛"
  },
  {
    "Word": "compile",
    "Mean": "vt.编辑  编制 编译 编纂 搜集"
  },
  {
    "Word": "complain",
    "Mean": "vi.抱怨  拆苦 悲叹 控告 控诉"
  },
  {
    "Word": "complaint",
    "Mean": "n.抱怨  怨言 控告"
  },
  {
    "Word": "complete",
    "Mean": "adj.完整的  完成的  彻底的  vt.完成  使圆满  使完美"
  },
  {
    "Word": "completely",
    "Mean": "adv.十分  完全地  全然"
  },
  {
    "Word": "complex",
    "Mean": "adj.结合的  复杂的  n.复合体"
  },
  {
    "Word": "complicate",
    "Mean": "vt.使复杂  使陷入  使错综  使起纠纷"
  },
  {
    "Word": "complicated",
    "Mean": "adj.复杂的  难懂的"
  },
  {
    "Word": "component",
    "Mean": "n.组成部分  分 组件 元件 成份 adj.组成的  构成的"
  },
  {
    "Word": "compose",
    "Mean": "vt.组成  构成 创作 写作 作曲 使镇静  vi.创作"
  },
  {
    "Word": "composition",
    "Mean": "n.构成  作品 写作 作文 著作 组织 合成物  成份"
  },
  {
    "Word": "compound",
    "Mean": "n. 化合物  混合物  复合词  adj. 复(混)合的  合成的  vt. 混合 调合 妥协 vi. 混合 妥协"
  },
  {
    "Word": "comprehension",
    "Mean": "n.理解  理解力  领悟"
  },
  {
    "Word": "comprehensive",
    "Mean": "adj.广泛的  理解的  综合的"
  },
  {
    "Word": "compress",
    "Mean": "vt.压紧  压缩 [计算机]  压缩"
  },
  {
    "Word": "comprise",
    "Mean": "vt.包含  包括 构成"
  },
  {
    "Word": "compromise",
    "Mean": "n.妥协  让步 和解 折衷 折衷案  vt.妥协处理  危害 vi.妥协 让步"
  },
  {
    "Word": "compute",
    "Mean": "vt.计算  估计 估算"
  },
  {
    "Word": "computer",
    "Mean": "n.计算机  电脑"
  },
  {
    "Word": "comrade",
    "Mean": "n.同志  亲密的同伴"
  },
  {
    "Word": "conceal",
    "Mean": "vt.把...隐藏起来   掩盖"
  },
  {
    "Word": "concentrate",
    "Mean": "vt. & vi.集中  专心 聚集 浓缩 n.浓缩  精选"
  },
  {
    "Word": "concentration",
    "Mean": "n.集中  专心 专注 浓缩 浓度"
  },
  {
    "Word": "concept",
    "Mean": "n.概念  观念 设想"
  },
  {
    "Word": "concern",
    "Mean": "n.关心(人或事)   忧虑 挂念 关系 公司 企业 vt.涉及  影响 关 心"
  },
  {
    "Word": "concerning",
    "Mean": "prep.关于"
  },
  {
    "Word": "concert",
    "Mean": "n.音乐会  演奏会  一致 和谐 vt.制定计划  通过协商达成一致 vi.合作"
  },
  {
    "Word": "conclude",
    "Mean": "vt.推断出  使结束  缔结 断定 得出结论  vi.结束  作出决定"
  },
  {
    "Word": "conclusion",
    "Mean": "n.结论  推论 结尾"
  },
  {
    "Word": "concrete",
    "Mean": "n.水泥  混凝土  具体物  adj.具体的  实在的  水泥的  vt. & vi. 凝结 结合"
  },
  {
    "Word": "condemn",
    "Mean": "vt.谴责  指责 判刑 官方宣称(某事物)有缺陷或不宜使用"
  },
  {
    "Word": "condense",
    "Mean": "vt.压缩  使缩短  浓缩 摘要"
  },
  {
    "Word": "condition",
    "Mean": "n.状况  状态 环境 条件 v.以...为条件   决定 支配 训练"
  },
  {
    "Word": "conduct",
    "Mean": "n.举止  行为 品行 指导 vi.引导  指挥 管理 vt.导电  传热"
  },
  {
    "Word": "conductor",
    "Mean": "n.售票员  (乐队)指挥  导体"
  },
  {
    "Word": "conference",
    "Mean": "n.会议  讨论会"
  },
  {
    "Word": "confess",
    "Mean": "vt.供认  承认 坦白 告白 忏悔"
  },
  {
    "Word": "confidence",
    "Mean": "n.信任  信赖 信心 把握 adj.骗得信任的"
  },
  {
    "Word": "confident",
    "Mean": "adj.确信的  自信的"
  },
  {
    "Word": "confine",
    "Mean": "vt.限制  禁闭 n.边界  约束 范围 限制"
  },
  {
    "Word": "confirm",
    "Mean": "vt.证实  肯定 批准 确定"
  },
  {
    "Word": "conflict",
    "Mean": "n.争论  冲突 斗争 战斗 矛盾 vi.争执  撞斗 冲突 [计算机] 冲突"
  },
  {
    "Word": "confuse",
    "Mean": "vt.使混乱  混淆 狼狈 困惑"
  },
  {
    "Word": "confusion",
    "Mean": "n.混乱  骚乱 混淆 不确定状态"
  },
  {
    "Word": "congratulate",
    "Mean": "vt.祝贺  向...道喜"
  },
  {
    "Word": "congratulation",
    "Mean": "n.祝贺  祝贺词"
  },
  {
    "Word": "congress",
    "Mean": "n.大会  国会 议会 集会"
  },
  {
    "Word": "conjunction",
    "Mean": "n.接合  连接 连接词  关联 (事件等的)同时发生"
  },
  {
    "Word": "connect",
    "Mean": "vt.连接  连结 联通 联系 使有联系"
  },
  {
    "Word": "connection",
    "Mean": "n.连接  联系 关系 亲戚 连贯性"
  },
  {
    "Word": "conquer",
    "Mean": "vt.征服  战胜 克服 破除 vi.得胜"
  },
  {
    "Word": "conquest",
    "Mean": "n.攻取  征服 克服"
  },
  {
    "Word": "conscience",
    "Mean": "n.良心  道德心  责任心  顾忌"
  },
  {
    "Word": "conscious",
    "Mean": "adj.意识到的   神志清醒的  意识到的  自觉的  有意的  n.意识"
  },
  {
    "Word": "consciousness",
    "Mean": "n.意识  觉悟 知觉 自觉"
  },
  {
    "Word": "consent",
    "Mean": "n.同意  赞成 许可 vi.同意  承诺"
  },
  {
    "Word": "consequence",
    "Mean": "n.结果  后果"
  },
  {
    "Word": "consequently",
    "Mean": "adv.因此  因而 所以"
  },
  {
    "Word": "conservation",
    "Mean": "n.保存  保护 守恒 防止流失  守恒 保护自然资源"
  },
  {
    "Word": "conservative",
    "Mean": "adj.保守的  守旧的  n.保守的人  保守派(党)"
  },
  {
    "Word": "consider",
    "Mean": "vt.认为  考虑 思考 关心"
  },
  {
    "Word": "considerable",
    "Mean": "adj.相当大的   重要的  可观的"
  },
  {
    "Word": "considerate",
    "Mean": "adj.考虑周到的   体谅的"
  },
  {
    "Word": "consideration",
    "Mean": "n.考虑  思考 体贴 考虑因素  敬重 意见"
  },
  {
    "Word": "consist",
    "Mean": "vi.由...组成   存在 一致 在于 n.组成"
  },
  {
    "Word": "consistent",
    "Mean": "adj.坚持的  一贯的  始终如一的  一致的"
  },
  {
    "Word": "constant",
    "Mean": "adj.经常的  永恒的  不变的n.常数   恒量"
  },
  {
    "Word": "constitution",
    "Mean": "n.章程  体质 构造 组织 宪法 体格"
  },
  {
    "Word": "construct",
    "Mean": "vt.建造  建设 构筑 绘制 想出 n.构想  建造物"
  },
  {
    "Word": "construction",
    "Mean": "n.建造  建设 建筑 建筑物  结构 构造"
  },
  {
    "Word": "consult",
    "Mean": "vt.向...请教   查阅 商讨"
  },
  {
    "Word": "consume",
    "Mean": "vt.消耗  消费 消灭 毁灭 吃、喝、挥霍   vi.耗尽生命  被烧毁"
  },
  {
    "Word": "consumption",
    "Mean": "n.消耗量  消耗 消费"
  },
  {
    "Word": "contact",
    "Mean": "vt.使接触  与...联系  n.接触  联系 联系人  adj.接触的"
  },
  {
    "Word": "contain",
    "Mean": "vt.包含  容纳 等于 克制 抑制 vi.自制"
  },
  {
    "Word": "container",
    "Mean": "n.容器  集装箱"
  },
  {
    "Word": "contemporary",
    "Mean": "adj.当代的  同时代的  同时的  现代的  n.同时代的人"
  },
  {
    "Word": "contempt",
    "Mean": "n.轻蔑  藐视 受辱"
  },
  {
    "Word": "content",
    "Mean": "n.内容  目录 容量 adj.满足的  满意的  vt.使...满足   使...安 心"
  },
  {
    "Word": "contest",
    "Mean": "vt.争夺  争取 辩驳 竞赛 vi.奋斗  n.竞赛  比赛"
  },
  {
    "Word": "continent",
    "Mean": "n.大陆  陆地 洲 (the Continent)欧洲大陆"
  },
  {
    "Word": "continual",
    "Mean": "adj.不断的  连续的  频繁的"
  },
  {
    "Word": "continue",
    "Mean": "vt. & vi.继续  连续 维持 延伸"
  },
  {
    "Word": "continuous",
    "Mean": "adj.连续不断的   连续的  继续的  连绵不断的  持续的"
  },
  {
    "Word": "contract",
    "Mean": "n.契约  合同书  合同 婚约 v.缩短  缩小 vt.订约"
  },
  {
    "Word": "contradiction",
    "Mean": "n.矛盾  不一致  否认 反驳"
  },
  {
    "Word": "contrary",
    "Mean": "adj.相反的  截然不同的  n.相反  反面 adv.相反(地)"
  },
  {
    "Word": "contrast",
    "Mean": "n.对比  对照 悬殊 差别 v.对比  成对照  [计算机]  反差"
  },
  {
    "Word": "contribute",
    "Mean": "vt.捐献  捐助 投稿 vi.投稿  贡献 是原因之一"
  },
  {
    "Word": "control",
    "Mean": "vt.控制  克制 掌管 支配 n.克制  控制 管制 操作装置"
  },
  {
    "Word": "convenience",
    "Mean": "n.便利  方便 便利设施  厕所 适宜 方便的时间  舒适"
  },
  {
    "Word": "convenient",
    "Mean": "adj.便利的  近便的  方便的"
  },
  {
    "Word": "convention",
    "Mean": "n.习俗  惯例 公约 大会 协定 [计算机]  约定"
  },
  {
    "Word": "conventional",
    "Mean": "adj.普通的  习惯的  传统的  惯例的  常规的"
  },
  {
    "Word": "conversation",
    "Mean": "n.会话  谈话 非正式会谈"
  },
  {
    "Word": "conversely",
    "Mean": "adv.相反地"
  },
  {
    "Word": "conversion",
    "Mean": "n.转变  转化 改变 改变信仰  换位"
  },
  {
    "Word": "convert",
    "Mean": "vt.使转变  使改变  倒置 n.皈依者  改宗者"
  },
  {
    "Word": "convey",
    "Mean": "vt.传送  运送 传播 转移 [计算机]  输送"
  },
  {
    "Word": "convince",
    "Mean": "vt.使确信  使信服  说服 使...相信"
  },
  {
    "Word": "cook",
    "Mean": "vt.烹调  煮 编造 虚构 烧(菜)  vi.烧菜  发生 做好 n.厨师  烧 菜"
  },
  {
    "Word": "cool",
    "Mean": "adj.凉的  冷静的  冷色系的  adv.冷静地  n.凉快  vt. & vi.(使)变凉  (使)冷静"
  },
  {
    "Word": "cooperate",
    "Mean": "vi.合作  协作 配合"
  },
  {
    "Word": "coordinate",
    "Mean": "vt.使协调  调节 整合 使一致  [计算机]  坐标 n. 同等的人物 (色调 图案 样式等)配套服装   adj. 同等的  等位的  (大学)男女 分院制的"
  },
  {
    "Word": "cope",
    "Mean": "vi.对付  应付 对抗 n.长袍  斗篷状物  vt.笼罩"
  },
  {
    "Word": "copper",
    "Mean": "n.铜 铜币 铜制器  有紫铜色翅膀的小蝴蝶    警官 vt.镀铜"
  },
  {
    "Word": "copy",
    "Mean": "n.抄件  副本 模仿 一册 稿件 vt.抄写  抄袭 复制 复印 vi.复 制 抄写 n. [计算机]  DOS命令：复制组合文件    拷贝"
  },
  {
    "Word": "cord",
    "Mean": "n.细绳  粗线 索 束缚 vt.用绳索绑"
  },
  {
    "Word": "cordial",
    "Mean": "adj.真诚的  诚恳的  热忱的  兴奋的  n.兴奋剂  补品"
  },
  {
    "Word": "core",
    "Mean": "n.果实的心  核心 要点 vt.挖去果核"
  },
  {
    "Word": "corn",
    "Mean": "n.谷物  谷粒 陈词滥调  鸡眼 (英)小麦  vt.使成颗粒状   用盐水 腌制 用谷物喂  vi.变成颗粒"
  },
  {
    "Word": "corner",
    "Mean": ".n 角 角落 转角 窘境 犄角 边远地区  偏僻住所  [计算机]  角 点 vt. 使...走投无路   使...陷入绝境   垄断 转弯adj.位于角落"
  },
  {
    "Word": "corporation",
    "Mean": "n.公司  法人 集团 企业 社团"
  },
  {
    "Word": "correct",
    "Mean": "adj.正确的  vt. & vi.改正  纠正"
  },
  {
    "Word": "correction",
    "Mean": "n.改正  纠正 修改 改正的地方"
  },
  {
    "Word": "correspond",
    "Mean": "vi.相符合  相当 通信"
  },
  {
    "Word": "correspondent",
    "Mean": "n.通信者  通讯记者  通讯员  adj.与...一致的   相应的"
  },
  {
    "Word": "corresponding",
    "Mean": "adj.相应的  符合的  一致的  相同的  相当的"
  },
  {
    "Word": "corridor",
    "Mean": "n.走廊  回廊 通路"
  },
  {
    "Word": "cost",
    "Mean": "n.价格  代价 成本 费用 vt.花费  使付出  vi.值 付出 [计算 机] 费用"
  },
  {
    "Word": "costly",
    "Mean": "adj.昂贵的  价值高的  代价高的"
  },
  {
    "Word": "cottage",
    "Mean": "n.村舍  小屋"
  },
  {
    "Word": "cotton",
    "Mean": "n.棉 棉花 棉线 棉布 vi.向...讨好  明白 领悟"
  },
  {
    "Word": "cough",
    "Mean": "vt. & vi.咳 咳嗽 n.咳嗽"
  },
  {
    "Word": "could",
    "Mean": "aux.v.(can的过去式)"
  },
  {
    "Word": "council",
    "Mean": "n.理事会  委员会  商议"
  },
  {
    "Word": "count",
    "Mean": "vt.计算  视为 依赖 vi.数 计数 n.计数"
  },
  {
    "Word": "counter",
    "Mean": "n.柜台  计数器  计算者  [计算机]  计数器  adj.相反的  adv.与 ...相反地  vt.反对  反击 vi.反对  反击"
  },
  {
    "Word": "country",
    "Mean": "n.国家  国土 农村 adj.国家(的)   农村(的)"
  },
  {
    "Word": "countryside",
    "Mean": "n.乡下  农村"
  },
  {
    "Word": "county",
    "Mean": "n.英国的郡  美国的县"
  },
  {
    "Word": "couple",
    "Mean": "n.夫妇  (一)对  几个 数个 v.加倍  成双 连结"
  },
  {
    "Word": "courage",
    "Mean": "n.勇气  胆量 胆识"
  },
  {
    "Word": "course",
    "Mean": "n.课程  讲座 过程 路线 一道菜"
  },
  {
    "Word": "court",
    "Mean": "n.法院  法庭 庭院 奉承 球场 v.献殷勤  追求 招致危险"
  },
  {
    "Word": "cousin",
    "Mean": "n.堂(或表)兄弟(姐妹)"
  },
  {
    "Word": "cover",
    "Mean": "vt.盖 覆盖 包括 涉及 包含n.盖子  封面 表面"
  },
  {
    "Word": "cow",
    "Mean": "n.母牛  奶牛 母兽"
  },
  {
    "Word": "coward",
    "Mean": "n.懦夫  胆怯者  adj.胆小的"
  },
  {
    "Word": "crack",
    "Mean": "n.裂缝  裂纹 声变 vi.爆裂  破裂 声变 打开"
  },
  {
    "Word": "craft",
    "Mean": "n.工艺  手艺 行业 航空器"
  },
  {
    "Word": "crane",
    "Mean": "n.起重机  摄影升降机  鹤 v.引颈  伸长(脖子)  vt.伸长(脖子 等)"
  },
  {
    "Word": "crash",
    "Mean": "vi.碰撞  坠落 猛使...破碎  迫降 n.碰撞  猛撞 轰隆声  崩溃 破产 垮台"
  },
  {
    "Word": "crawl",
    "Mean": "vi.爬 爬行 n.爬行  匍匐而行"
  },
  {
    "Word": "crazy",
    "Mean": "adj.疯狂的  荒唐的"
  },
  {
    "Word": "cream",
    "Mean": "n.奶油  乳酪 乳脂 奶油色  面霜 精华"
  },
  {
    "Word": "create",
    "Mean": "vt.创造  引起 产生"
  },
  {
    "Word": "creative",
    "Mean": "adj.创造性的   创作的"
  },
  {
    "Word": "creature",
    "Mean": "n.生物  动物 家畜 人"
  },
  {
    "Word": "单词",
    "Mean": "释义"
  },
  {
    "Word": "credit",
    "Mean": "n.信用贷款  信用 荣誉 学分 v.归功于  赞颂 信任"
  },
  {
    "Word": "creep",
    "Mean": "vi.爬行  缓慢地行进  蔓延 n.爬 徐行 蠕动"
  },
  {
    "Word": "crew",
    "Mean": "n.全体船员  全体乘务员  vi.一起工作"
  },
  {
    "Word": "cricket",
    "Mean": "n.板球  蟋蟀 vi.打板球"
  },
  {
    "Word": "crime",
    "Mean": "n.罪 罪行 犯罪 羞耻"
  },
  {
    "Word": "criminal",
    "Mean": "n.犯人  罪犯 刑事犯  adj.犯罪的  刑事的  无耻的"
  },
  {
    "Word": "cripple",
    "Mean": "n.跛子  残废的人  v.使...跛  使...成残废  削弱"
  },
  {
    "Word": "crisis",
    "Mean": "n.危机  存亡之际"
  },
  {
    "Word": "critic",
    "Mean": "n.批评家  评论家  爱挑剔的人"
  },
  {
    "Word": "critical",
    "Mean": "adj.决定性的   批评的  危险的  挑剔的  临界的"
  },
  {
    "Word": "criticism",
    "Mean": "n.批评  批判 评论"
  },
  {
    "Word": "criticize",
    "Mean": "vt.批评  评论 非难 吹毛求疵  vi.批评"
  },
  {
    "Word": "crop",
    "Mean": "n.农作物  庄稼 收成 一熟 一群 平头 vt.割掉  修剪 剪短 收 割 使谷物生长  vi.啃青草  种植谷物"
  },
  {
    "Word": "cross",
    "Mean": "vt.穿过  划叉剔除  画横线于  vi.穿越  prep.穿过  n.十字架  十 字架形物件  交叉 交叉路  adj.生气的  交叉的"
  },
  {
    "Word": "crow",
    "Mean": "n.鸦 乌鸦 啼叫 欢叫 vi.啼 啼叫 报晓 欢叫 vt.洋洋夸口  自 鸣得意"
  },
  {
    "Word": "crowd",
    "Mean": "n.群 大众 一伙人  一堆 vi.拥挤  挤满 挤进 vt.挤满  将...塞 进 催促"
  },
  {
    "Word": "crown",
    "Mean": "n.王冠  冕 王权 顶点 花冠 vt.使...成王   加冕 居...之顶  为 牙齿镶上假齿冠   vi.火迅速烧到树的顶端"
  },
  {
    "Word": "crude",
    "Mean": "adj.简陋的  天然的  未加工的  粗鲁的  n.原油"
  },
  {
    "Word": "cruel",
    "Mean": "adj.残忍的  残酷的  引起痛苦的"
  },
  {
    "Word": "crush",
    "Mean": "vt.压碎  碾碎 镇压 拥挤的人群  迷恋 关键时刻  果汁 榨汁酿 酒 vt.压破  征服 挤入 镇压 vi.被压碎  挤"
  },
  {
    "Word": "crust",
    "Mean": "n.面包皮  硬外皮  外壳 坚硬的外壳  vt.盖以硬皮  vi.结硬皮"
  },
  {
    "Word": "cry",
    "Mean": "vi.哭 哭泣 叫喊 强烈要求  vt.大声叫喊  宣传 哭得...  n.叫 哭 喊 口号 叫卖声  普遍意见"
  },
  {
    "Word": "crystal",
    "Mean": "n.水晶  结晶体  晶粒adj.清澈透明的    晶体的"
  },
  {
    "Word": "cube",
    "Mean": "n.立方体  立方 vt.求...的立方   adj.立方的"
  },
  {
    "Word": "cubic",
    "Mean": "adj.立方体的   立方的"
  },
  {
    "Word": "cucumber",
    "Mean": "n.黄瓜"
  },
  {
    "Word": "cultivate",
    "Mean": "vt.耕 种植 培养 栽培 结交(朋友)  促进增长  教养"
  },
  {
    "Word": "culture",
    "Mean": "n.文化  文明 教养 种植 vt.培养"
  },
  {
    "Word": "cunning",
    "Mean": "adj.狡猾的  狡诈的  有眼光的  精巧的  可爱的  n.狡诈  灵巧"
  },
  {
    "Word": "cup",
    "Mean": "n.杯子  (一)杯  奖杯 v.(使)成杯形   vt.使成杯形"
  },
  {
    "Word": "cupboard",
    "Mean": "n.碗柜  碗碟橱  食橱"
  },
  {
    "Word": "cure",
    "Mean": "vt.医治  消除 vt. &vi.治疗  治愈 改正 n.治疗  治愈 治疗法"
  },
  {
    "Word": "curiosity",
    "Mean": "n.好奇  好奇心  珍品"
  },
  {
    "Word": "curious",
    "Mean": "adj.好奇的  奇特的  稀奇古怪的"
  },
  {
    "Word": "curl",
    "Mean": "n.卷毛  螺旋 vi.卷曲  弄卷 弯曲"
  },
  {
    "Word": "current",
    "Mean": "adj.当前的  现在的  最近的  通用的  流通的  n.(水、气、电)流 趋势"
  },
  {
    "Word": "curse",
    "Mean": "n.诅咒  咒骂 天谴 祸端 行经 vt.咒骂  诅咒 引起灾祸  vi.诅 咒"
  },
  {
    "Word": "curtain",
    "Mean": "n.帘 窗帘 幕(布)  遮蔽物  vt.用窗帘装饰   遮蔽"
  },
  {
    "Word": "curve",
    "Mean": "n.曲线  弯 弯曲 曲球 vt.弄弯  使...弯曲  vi.弯曲"
  },
  {
    "Word": "cushion",
    "Mean": "n.垫子  坐垫 橡皮软垫  缓冲 vt.加垫褥  放在垫子上  保护 减 缓 为...装垫子"
  },
  {
    "Word": "custom",
    "Mean": "n.习惯  风俗 海关"
  },
  {
    "Word": "customer",
    "Mean": "n.顾客  主顾 家伙"
  },
  {
    "Word": "cut",
    "Mean": "vt. 切 割 剪 减少 停止 修剪 vi. 切割 快速移动  [计算机] 剪掉 n. 切口 割伤 降低 份额 删节 割下的一块肉"
  },
  {
    "Word": "cycle",
    "Mean": "n自行车  循环 周期 长期 圈 套曲 vt.环行  骑自行车  vi.使环 行"
  }
]