[{
  "Word": "vacant",
  "Mean": "adj.空的  空虚的  木然的  未被占用的"
},
  {
    "Word": "vacation",
    "Mean": "n.假期  休假 腾出 vi.度假"
  },
  {
    "Word": "vacuum",
    "Mean": "n.真空  空间 真空吸尘器  adj.真空的  产生(利用)真空的   v.用 吸尘器打扫"
  },
  {
    "Word": "vague",
    "Mean": "adj.模糊的  含糊的  不明确的  犹豫不决的  茫然的"
  },
  {
    "Word": "vain",
    "Mean": "adj.徒劳的  无效的  自负的  虚荣的"
  },
  {
    "Word": "valid",
    "Mean": "adj.有效的  有根据的  正当的  合法的"
  },
  {
    "Word": "valley",
    "Mean": "n.(山)谷  溪谷 流域 adj.流域  山谷 峡谷"
  },
  {
    "Word": "valuable",
    "Mean": "adj.值钱的  有价值的  n.(pl.)贵重物品"
  },
  {
    "Word": "value",
    "Mean": "n.价值  重要性  价格 (pl)价值观  vt.评价  估价 重视"
  },
  {
    "Word": "van",
    "Mean": "n.大篷车  运货车  面包车  vt.(用货车)运   n.前卫  前锋 n.翼"
  },
  {
    "Word": "vanish",
    "Mean": "vi.突然不见  消失 绝迹 vt.消失"
  },
  {
    "Word": "vanity",
    "Mean": "n.虚荣心  虚夸 浮华 无价值的东西   adj.虚荣心的"
  },
  {
    "Word": "vapour",
    "Mean": "n.汽 蒸气 雾气 v.蒸发  吹嘘 =vapor(英)"
  },
  {
    "Word": "variable",
    "Mean": "adj.易变的  可变的  n.变量  易变的东西"
  },
  {
    "Word": "variation",
    "Mean": "n.变化  变动 变异 变种 变奏曲"
  },
  {
    "Word": "variety",
    "Mean": "n.多样化  种类 变种 杂耍"
  },
  {
    "Word": "various",
    "Mean": "adj.各种各样的   不同的"
  },
  {
    "Word": "vary",
    "Mean": "vt.改变  变化 使多样化"
  },
  {
    "Word": "vase",
    "Mean": "n.瓶 花瓶"
  },
  {
    "Word": "vast",
    "Mean": "adj.巨大的  大量的  广阔的  n.浩瀚的太空"
  },
  {
    "Word": "vegetable",
    "Mean": "n.植物  蔬菜 植物人adj.蔬菜的   植物的"
  },
  {
    "Word": "vehicle",
    "Mean": "n.车辆  机动车  交通工具  手段 工具 传播媒介"
  },
  {
    "Word": "veil",
    "Mean": "n.面纱  面罩 遮蔽物  掩饰物  修女 vt.给...戴面纱或面罩    vi. 带面纱或面罩"
  },
  {
    "Word": "velocity",
    "Mean": "n.速度  速率 迅速"
  },
  {
    "Word": "velvet",
    "Mean": "n.丝绒  天鹅绒  adj.天鹅绒的"
  },
  {
    "Word": "venture",
    "Mean": "n. & vi.冒险  风险 投机 vt.敢于  尝试 谨慎地做  冒险一试"
  },
  {
    "Word": "verb",
    "Mean": "n.动词"
  },
  {
    "Word": "verify",
    "Mean": "vt.证实  查证 证明 核实"
  },
  {
    "Word": "version",
    "Mean": "n.译文  说法 改写本  版本 译本 形式"
  },
  {
    "Word": "vertical",
    "Mean": "a.垂直的  竖式的  顶点的  纵向的  n.垂直物  垂直的位置"
  },
  {
    "Word": "very",
    "Mean": "adv.很  完全 真正地  adj.真的  真正的  同一的  仅仅的  恰好的"
  },
  {
    "Word": "vessel",
    "Mean": "n.容器  器皿 船 飞船 管 脉管 血管 [植]导管"
  },
  {
    "Word": "vest",
    "Mean": "n.汗衫  背心 马甲 内衣 vt.授予  给予 使穿衣  vi.(权力、财 产等)归于  穿衣服"
  },
  {
    "Word": "veteran",
    "Mean": "n.老兵  老手 adj.老练的"
  },
  {
    "Word": "vex",
    "Mean": "vt.使烦恼  使恼火  恼怒"
  },
  {
    "Word": "via",
    "Mean": "prep.经过  通过"
  },
  {
    "Word": "vibrate",
    "Mean": "vt.使颤动  (使)振动  (使)摇摆vi.颤动   回响"
  },
  {
    "Word": "vibration",
    "Mean": "n.颤动  振动 摆动"
  },
  {
    "Word": "vice",
    "Mean": "n.罪恶  恶习 缺点 邪恶 老虎钳  adj.副的  代理的  prep.代替"
  },
  {
    "Word": "victim",
    "Mean": "n.牺牲者  受害者  牺牲"
  },
  {
    "Word": "victorious",
    "Mean": "adj.胜利的  得胜的"
  },
  {
    "Word": "victory",
    "Mean": "n.胜利  战胜 成功"
  },
  {
    "Word": "video",
    "Mean": "adj.电视的  视频的  录像的n.电视   视频 录像"
  },
  {
    "Word": "view",
    "Mean": "n.看 视力 风景 视野 见解 方法 检查"
  },
  {
    "Word": "viewpoint",
    "Mean": "n.观点  看法 见解"
  },
  {
    "Word": "vigorous",
    "Mean": "adj.朝气蓬勃的   精力充沛的  元气旺盛的  有力的"
  },
  {
    "Word": "village",
    "Mean": "n.乡村  村庄"
  },
  {
    "Word": "vine",
    "Mean": "n.葡萄树  攀爬植物  藤 蔓"
  },
  {
    "Word": "vinegar",
    "Mean": "n.醋"
  },
  {
    "Word": "violence",
    "Mean": "n.猛烈  激烈 暴力 强暴 暴行"
  },
  {
    "Word": "violent",
    "Mean": "adj.猛烈的  狂暴的  暴力的  极端的"
  },
  {
    "Word": "violet",
    "Mean": "n.紫罗兰  紫色 adj.紫色的"
  },
  {
    "Word": "violin",
    "Mean": "n.小提琴"
  },
  {
    "Word": "virtually",
    "Mean": "ad.v实际上  事实上  几乎"
  },
  {
    "Word": "virtue",
    "Mean": "n.善 美德 优点 德行 贞操"
  },
  {
    "Word": "visible",
    "Mean": "adj.可见的  看得见的  n.可见物"
  },
  {
    "Word": "vision",
    "Mean": "n.视力  视觉 眼力 想象力  梦幻 幻觉 vt.幻想  设想"
  },
  {
    "Word": "visit",
    "Mean": "vt. & n.访问  参观 拜访 探访"
  },
  {
    "Word": "visitor",
    "Mean": "n.访问者  游客 参观者"
  },
  {
    "Word": "visual",
    "Mean": "adj.看的  看得见的,  视觉的  n.画面  图象"
  },
  {
    "Word": "vital",
    "Mean": "adj.生命的  有生命力的  至关重要的  生死攸关的  有活力的"
  },
  {
    "Word": "vitamin",
    "Mean": "n.维生素  维他命"
  },
  {
    "Word": "vivid",
    "Mean": "adj.鲜艳的  生动的  栩栩如生的"
  },
  {
    "Word": "vocabulary",
    "Mean": "n.词汇表  词汇 语汇 词汇量"
  },
  {
    "Word": "voice",
    "Mean": "n.说话声  声音 嗓音 意见 [语]语态  意见 发言权  vt.表达  发 音 调整声音"
  },
  {
    "Word": "volcano",
    "Mean": "n.火山"
  },
  {
    "Word": "volleyball",
    "Mean": "n.排球  排球运动"
  },
  {
    "Word": "volt",
    "Mean": "n.(电压单位)伏特   伏 voltage  ['v ə ultid ʒ ] n.电压"
  },
  {
    "Word": "volume",
    "Mean": "n.卷 册 容积 体积 音量"
  },
  {
    "Word": "voluntary",
    "Mean": "adj.自愿的  志愿的  n.(教堂礼拜仪式前后或进行期间的)乐器 独奏"
  },
  {
    "Word": "vote",
    "Mean": "n.选举  投票 表决 投票结果  选举权  v.投票  选举 表决"
  },
  {
    "Word": "voyage",
    "Mean": "n. & vi.航海  航空 航行 旅行 旅程"
  }
]